{
  "name": "Lydia Diaz",
  "age": 49,
  "address": {
    "street": "Tebas Heights",
    "city": "Kulnihso",
    "state": "NV",
    "zip": "12886"
  },
  "contact": {
    "phone": "(312) 930-1649",
    "servicePhone": "800778621"
  },
  "birthday": "1959-10-28T06:07:26.875Z",
  "ip": "119.15.201.190",
  "foo": "bar",
  "profile": {
    "about": "Pu sal mum zomhawlon turim iv uwijumut adenuva ap mov poz hezge sel ucosu cufzujem. Wizmosig wisfi co pas rakekfa iweke potuc besreb op peflav edecmu fagikha kuv wiri bihig wirarram wappa na. Sefek ifi rujcena munawhu mu fuwlohse jogcekmid acepezzoz muef rursoega foc evvu. Lomatu nef fuavepe alomiglo luga ojbo lesa iszoj ji herpupap huwpim ice kol. Ebu na gepasjub pi afuti udi uga iwumo get gukrajnu mawovo ginef nufhilo doktari cof liw diickif.",
    "bio": "Moni ta fij co nipedlus pu repfues fozwi kuzmis bawu ki ejdo. Ida ejfopsap ciwtodli dapmupki cizteso ilikiji gatneme utakirde zulaihe mun sa ze vi munmofak. Ravo ago oda ruil uzihopdi pijsifid uwe fuzpi zuhhic zuhep receala ic iz bik kic wo sarru ok. Nimazat am gawu nekkurzuh nok mu bahkas uj eg jo kamtofek pogneij."
  },
  "apiKey": "54f6506eba51848e62abb20728dbd7419a73163815a3d1c1de0548101953c15a",
  "currency": {
    "code": "ISK",
    "name": "Iceland Krona"
  }
}